[{"USERJID":"5581996902292@s.whatsapp.net"},{"USERJID":"5531997081595@s.whatsapp.net"},{"USERJID":"5583998336345@s.whatsapp.net"},{"USERJID":"5519994769877@s.whatsapp.net"},{"USERJID":"5586981900752@s.whatsapp.net"},{"USERJID":"5513991402655@s.whatsapp.net"},{"USERJID":"5584999078877@s.whatsapp.net"},{"USERJID":"5515998280441@s.whatsapp.net"},{"USERJID":"5515996204991@s.whatsapp.net"},{"USERJID":"5515996074681@s.whatsapp.net"},{"USERJID":"5515981127911@s.whatsapp.net"},{"USERJID":"5511999951213@s.whatsapp.net"},{"USERJID":"5515998450544@s.whatsapp.net"},{"USERJID":"5511978989582@s.whatsapp.net"},{"USERJID":"5581994265364@s.whatsapp.net"},{"USERJID":"5581985641781@s.whatsapp.net"},{"USERJID":"5545991223320@s.whatsapp.net"},{"USERJID":"5581998413711@s.whatsapp.net"},{"USERJID":"5592991329465@s.whatsapp.net"},{"USERJID":"5598985198424@s.whatsapp.net"},{"USERJID":"5591991863809@s.whatsapp.net"},{"USERJID":"5511977214572@s.whatsapp.net"},{"USERJID":"5581999152203@s.whatsapp.net"},{"USERJID":"5598988820304@s.whatsapp.net"},{"USERJID":"5582987930756@s.whatsapp.net"},{"USERJID":"5522997784941@s.whatsapp.net"}]
